gstools_cython-1.2.0.dist-info/RECORD
gstools_cython-1.2.0.dist-info/WHEEL
gstools_cython-1.2.0.dist-info/top_level.txt
gstools_cython-1.2.0.dist-info/METADATA
gstools_cython-1.2.0.dist-info/licenses/LICENSE
gstools_cython/variogram.cpython-314-darwin.so
gstools_cython/field.cpython-314-darwin.so
gstools_cython/_version.py
gstools_cython/krige.cpython-314-darwin.so
gstools_cython/__init__.py
