Metadata-Version: 2.4
Name: gstools_cython
Version: 1.2.0
Summary: Cython backend for GSTools.
Author-email: "Sebastian Müller, Lennart Schüler" <info@geostat-framework.org>
License-Expression: LGPL-3.0-or-later
Project-URL: Changelog, https://github.com/GeoStat-Framework/GSTools-Cython/blob/main/CHANGELOG.md
Project-URL: Conda-Forge, https://anaconda.org/conda-forge/gstools
Project-URL: Documentation, https://gstools.readthedocs.io
Project-URL: Homepage, https://geostat-framework.org/#gstools
Project-URL: Source, https://github.com/GeoStat-Framework/GSTools-Cython
Project-URL: Tracker, https://github.com/GeoStat-Framework/GSTools-Cython/issues
Classifier: Development Status :: 5 - Production/Stable
Classifier: Intended Audience :: Developers
Classifier: Intended Audience :: End Users/Desktop
Classifier: Intended Audience :: Science/Research
Classifier: Intended Audience :: Education
Classifier: Natural Language :: English
Classifier: Operating System :: Unix
Classifier: Operating System :: Microsoft
Classifier: Operating System :: MacOS
Classifier: Programming Language :: Python
Classifier: Programming Language :: Python :: 3
Classifier: Programming Language :: Python :: 3 :: Only
Classifier: Programming Language :: Python :: 3.10
Classifier: Programming Language :: Python :: 3.11
Classifier: Programming Language :: Python :: 3.12
Classifier: Programming Language :: Python :: 3.13
Classifier: Programming Language :: Python :: 3.14
Classifier: Topic :: Scientific/Engineering
Classifier: Topic :: Scientific/Engineering :: GIS
Classifier: Topic :: Scientific/Engineering :: Hydrology
Classifier: Topic :: Scientific/Engineering :: Mathematics
Classifier: Topic :: Scientific/Engineering :: Physics
Classifier: Topic :: Utilities
Requires-Python: >=3.10
License-File: LICENSE
Requires-Dist: numpy>=1.20.0
Provides-Extra: doc
Requires-Dist: myst_parser; extra == "doc"
Requires-Dist: numpydoc; extra == "doc"
Requires-Dist: sphinx>=7; extra == "doc"
Requires-Dist: sphinx-rtd-theme>=3; extra == "doc"
Provides-Extra: test
Requires-Dist: pytest-cov>=3; extra == "test"
Requires-Dist: Cython>=3; extra == "test"
Provides-Extra: lint
Requires-Dist: black>=24; extra == "lint"
Requires-Dist: pylint; extra == "lint"
Requires-Dist: isort[colors]; extra == "lint"
Requires-Dist: cython-lint; extra == "lint"
Dynamic: license-file
